apsisocr/__init__.py
apsisocr/apsisnet.py
apsisocr/base.py
apsisocr/bnocr.py
apsisocr/bnocrbase.py
apsisocr/densenet121bnencls.py
apsisocr/modules.py
apsisocr/ocr.py
apsisocr/paddledbnet.py
apsisocr/paddlesvtr.py
apsisocr/utils.py
apsisocr-0.0.7.dist-info/METADATA
apsisocr-0.0.7.dist-info/WHEEL
apsisocr-0.0.7.dist-info/top_level.txt
apsisocr-0.0.7.dist-info/RECORD
