Metadata-Version: 2.1
Name: apsisocr
Version: 0.0.7
Summary: Bangla English Mixed Languge Scene / printed OCR Toolkit
Home-page: https://github.com/mnansary/apsis-ocr/
Author: Nazmuddoha Ansary
Author-email: nazmuddoha.ansary@apsissolutions.com
License: MIT
Keywords: ocr,multilingual-ocr,scene ocr,apsisnet
Classifier: Development Status :: 3 - Alpha
Classifier: Intended Audience :: Education
Classifier: Operating System :: POSIX :: Linux
Classifier: License :: OSI Approved :: MIT License
Classifier: Programming Language :: Python :: 3
Requires-Dist: numpy
Requires-Dist: matplotlib
Requires-Dist: opencv-python
Requires-Dist: pandas
Requires-Dist: tqdm
Requires-Dist: termcolor
Requires-Dist: gdown
Requires-Dist: bnunicodenormalizer
Requires-Dist: flask
Requires-Dist: flask-cors
Requires-Dist: streamlit
